{
	"info": {
		"_postman_id": "8a0b1a5e-2874-473f-9859-1900c34bfd59",
		"name": "blog_app_apis",
		"schema": "https://schema.getpostman.com/json/collection/v2.1.0/collection.json",
		"_exporter_id": "30945716"
	},
	"item": [
		{
			"name": "get user",
			"request": {
				"method": "GET",
				"header": [],
				"url": {
					"raw": "http://localhost:8080/api/users/getalluser",
					"protocol": "http",
					"host": [
						"localhost"
					],
					"port": "8080",
					"path": [
						"api",
						"users",
						"getalluser"
					]
				}
			},
			"response": []
		},
		{
			"name": "get single user",
			"request": {
				"method": "GET",
				"header": [],
				"url": {
					"raw": "http://localhost:8080/api/users/getbyid/2",
					"protocol": "http",
					"host": [
						"localhost"
					],
					"port": "8080",
					"path": [
						"api",
						"users",
						"getbyid",
						"2"
					]
				}
			},
			"response": []
		},

		
		{
			"name": "update user by  id",
			"request": {
				"method": "PUT",
				"header": [],
				"body": {
					"mode": "raw",
					"raw": "{\r\n\r\n    \"id\":1,\r\n    \"name\":\"adarsh3\",\r\n    \"email\":\"adarsh90021@gmail.com\",\r\n    \"password\": \"zzzaluu\",\r\n    \"about\":\"thisss is test two\"\r\n}",
					"options": {
						"raw": {
							"language": "json"
						}
					}
				},
				"url": {
					"raw": "http://localhost:8080/api/users/update/1",
					"protocol": "http",
					"host": [
						"localhost"
					],
					"port": "8080",
					"path": [
						"api",
						"users",
						"update",
						"1"
					]
				}
			},
			"response": []
		},
		{
			"name": "delete by id",
			"request": {
				"method": "DELETE",
				"header": [],
				"url": {
					"raw": "http://localhost:8080/api/users/delete/52",
					"protocol": "http",
					"host": [
						"localhost"
					],
					"port": "8080",
					"path": [
						"api",
						"users",
						"delete",
						"52"
					]
				}
			},
			"response": []
		},
		{
			"name": "add user",
			"request": {
				"method": "POST",
				"header": [],
				"body": {
					"mode": "raw",
					"raw": "{\r\n\r\n    \"name\":\"nandini\",\r\n    \"email\":\"nandini90021@gmail.com\",\r\n    \"password\": \"nanu\",\r\n    \"about\":\"this is test three\"\r\n}",
					"options": {
						"raw": {
							"language": "json"
						}
					}
				},
				"url": {
					"raw": "http://localhost:8080/api/users/",
					"protocol": "http",
					"host": [
						"localhost"
					],
					"port": "8080",
					"path": [
						"api",
						"users",
						""
					]
				}
			},
			"response": []
		},
		{
			"name": "create category",
			"request": {
				"method": "POST",
				"header": [],
				"body": {
					"mode": "raw",
					"raw": "{\r\n\"category_title\":\"gk \",\r\n\"category_discription\":\"knowledge\"\r\n\r\n}",
					"options": {
						"raw": {
							"language": "json"
						}
					}
				},
				"url": {
					"raw": "http://localhost:8080/api/category/",
					"protocol": "http",
					"host": [
						"localhost"
					],
					"port": "8080",
					"path": [
						"api",
						"category",
						""
					]
				}
			},
			"response": []
		},
		{
			"name": "get all cateogory",
			"request": {
				"method": "GET",
				"header": [],
				"url": {
					"raw": "http://localhost:8080/api/category/getall",
					"protocol": "http",
					"host": [
						"localhost"
					],
					"port": "8080",
					"path": [
						"api",
						"category",
						"getall"
					]
				}
			},
			"response": []
		},
		{
			"name": "get single category",
			"request": {
				"method": "GET",
				"header": [],
				"url": {
					"raw": "http://localhost:8080/api/category/singlecat/3",
					"protocol": "http",
					"host": [
						"localhost"
					],
					"port": "8080",
					"path": [
						"api",
						"category",
						"singlecat",
						"3"
					]
				}
			},
			"response": []
		},
		{
			"name": "delete category",
			"request": {
				"method": "DELETE",
				"header": [],
				"url": {
					"raw": "http://localhost:8080/api/category/delete/1",
					"protocol": "http",
					"host": [
						"localhost"
					],
					"port": "8080",
					"path": [
						"api",
						"category",
						"delete",
						"1"
					]
				}
			},
			"response": []
		},
		{
			"name": "update category",
			"request": {
				"method": "PUT",
				"header": [],
				"body": {
					"mode": "raw",
					"raw": "{\r\n\"category_title\":\"gkkk \",\r\n\"category_discription\":\"knowledgeee\"\r\n\r\n}",
					"options": {
						"raw": {
							"language": "json"
						}
					}
				},
				"url": {
					"raw": "http://localhost:8080/api/category/update/2",
					"protocol": "http",
					"host": [
						"localhost"
					],
					"port": "8080",
					"path": [
						"api",
						"category",
						"update",
						"2"
					]
				}
			},
			"response": []
		},
		{
			"name": "create post",
			"request": {
				"method": "GET",
				"header": []
			},
			"response": []
		},
		{
			"name": "get post by user",
			"request": {
				"method": "GET",
				"header": []
			},
			"response": []
		},
		{
			"name": "get post by category",
			"request": {
				"method": "GET",
				"header": [],
				"url": {
					"raw": "http://localhost:8080/api/category/2/posts",
					"protocol": "http",
					"host": [
						"localhost"
					],
					"port": "8080",
					"path": [
						"api",
						"category",
						"2",
						"posts"
					]
				}
			},
			"response": []
		},
		{
			"name": "get alll post",
			"request": {
				"method": "GET",
				"header": [],
				"url": {
					"raw": "http://localhost:8080/api/posts",
					"protocol": "http",
					"host": [
						"localhost"
					],
					"port": "8080",
					"path": [
						"api",
						"posts"
					]
				}
			},
			"response": []
		},
		{
			"name": "get post by id",
			"request": {
				"method": "GET",
				"header": [],
				"url": {
					"raw": "http://localhost:8080/api/posts/1",
					"protocol": "http",
					"host": [
						"localhost"
					],
					"port": "8080",
					"path": [
						"api",
						"posts",
						"1"
					]
				}
			},
			"response": []
		},
		{
			"name": "update post",
			"request": {
				"method": "PUT",
				"header": [],
				"body": {
					"mode": "raw",
					"raw": "{\r\n\"title\":\"what is java programming language by rajen\",\r\n\"content\":\"programming language used to communicate with machine by rajen\"\r\n}",
					"options": {
						"raw": {
							"language": "json"
						}
					}
				},
				"url": {
					"raw": "http://localhost:8080/api/posts/1",
					"protocol": "http",
					"host": [
						"localhost"
					],
					"port": "8080",
					"path": [
						"api",
						"posts",
						"1"
					]
				}
			},
			"response": []
		},
		{
			"name": "delete post",
			"request": {
				"method": "DELETE",
				"header": [],
				"url": {
					"raw": "http://localhost:8080/api/posts/3",
					"protocol": "http",
					"host": [
						"localhost"
					],
					"port": "8080",
					"path": [
						"api",
						"posts",
						"3"
					]
				}
			},
			"response": []
		},
		{
			"name": "search post",
			"request": {
				"method": "GET",
				"header": [],
				"url": {
					"raw": "http://localhost:8080/api/post/search?title=post 6",
					"protocol": "http",
					"host": [
						"localhost"
					],
					"port": "8080",
					"path": [
						"api",
						"post",
						"search"
					],
					"query": [
						{
							"key": "title",
							"value": "post 6"
						}
					]
				}
			},
			"response": []
		}
	]
}